MANIFEST.in
README.md
VERSION
setup.py
logbinsearch/__init__.py
logbinsearch/binsearch.py
logbinsearch/bz2bin.py
logbinsearch.egg-info/PKG-INFO
logbinsearch.egg-info/SOURCES.txt
logbinsearch.egg-info/dependency_links.txt
logbinsearch.egg-info/top_level.txt
logbinsearch/scripts/__init__.py
logbinsearch/scripts/logdatetimesearch.py
logbinsearch/test/__init__.py
logbinsearch/test/binsearch_test.py
logbinsearch/test/bz2search_test.py
logbinsearch/test/logdatetimesearch_test.py
logbinsearch/test/util.py
scripts/logdatetimesearch
src/bz2search.c
src/microbunzip.c
src/microbunzip.h