Metadata-Version: 1.0
Name: logbinsearch
Version: 0.0.6
Summary: search (bz2)log file with binary search
Home-page: https://github.com/takada-at/logbinsearch
Author: takada-at
Author-email: takada-at@klab.com
License: UNKNOWN
Platform: UNKNOWN
